FTPDownloader/FTPDirCache.py
FTPDownloader/FTPDownloader_exc.py
FTPDownloader/FTPDownloader_main.py
FTPDownloader/__init__.py
FTPDownloader/tests/__init__.py
FTPDownloader/tests/test_FTPDirCache.py
FTPDownloader/tests/test_FTPDownloader_main.py
FTPDownloader-1.3.0.dist-info/LICENSE.md
FTPDownloader-1.3.0.dist-info/METADATA
FTPDownloader-1.3.0.dist-info/WHEEL
FTPDownloader-1.3.0.dist-info/top_level.txt
FTPDownloader-1.3.0.dist-info/RECORD
