Metadata-Version: 2.1
Name: FTPDownloader
Version: 1.3.0
Summary: A tool to bulk download files from a FTP Server
Home-page: https://git.connect.dzd-ev.de/dzdpythonmodules/ftpdownloader
Author: TB
Author-email: tim.bleimehl@helmholtz-muenchen.de
License: MIT
Platform: UNKNOWN
Requires-Python: >=3.6
License-File: LICENSE.md
Requires-Dist: numpy
Requires-Dist: tqdm
